LICENSE
MANIFEST.in
README.rst
pytest_pact.py
setup.py
pytest_pact.egg-info/PKG-INFO
pytest_pact.egg-info/SOURCES.txt
pytest_pact.egg-info/dependency_links.txt
pytest_pact.egg-info/entry_points.txt
pytest_pact.egg-info/requires.txt
pytest_pact.egg-info/top_level.txt